README.md
setup.cfg
setup.py
src/artichoqe/__init__.py
src/artichoqe/main.py
src/artichoqe.egg-info/PKG-INFO
src/artichoqe.egg-info/SOURCES.txt
src/artichoqe.egg-info/dependency_links.txt
src/artichoqe.egg-info/entry_points.txt
src/artichoqe.egg-info/requires.txt
src/artichoqe.egg-info/top_level.txt
src/artichoqe.egg-info/zip-safe
src/artichoqe/commands/__init__.py
src/artichoqe/commands/aws/__init__.py
src/artichoqe/utils/__init__.py
src/artichoqe/utils/aws_helper.py